hub_scraper/__init__.py
hub_scraper/conf.py
hub_scraper/console/__init__.py
hub_scraper/console/application.py
hub_scraper/console/utils.py
hub_scraper/filters/__init__.py
hub_scraper/filters/article_filter.py
hub_scraper/filters/existed_filter.py
hub_scraper/filters/factory.py
hub_scraper/filters/min_datetime_filter.py
hub_scraper/filters/post_type_filter.py
hub_scraper/indexers/__init__.py
hub_scraper/indexers/factory.py
hub_scraper/indexers/indexer.py
hub_scraper/indexers/indexers/__init__.py
hub_scraper/indexers/indexers/default_obsidian/__init__.py
hub_scraper/indexers/indexers/default_obsidian/index_maker.py
hub_scraper/indexers/indexers/default_obsidian/models.py
hub_scraper/indexers/utils.py
hub_scraper/models/__init__.py
hub_scraper/models/article.py
hub_scraper/models/article_author.py
hub_scraper/models/article_listing.py
hub_scraper/models/article_meta.py
hub_scraper/models/data_folder.py
hub_scraper/models/hub.py
hub_scraper/scraper/__init__.py
hub_scraper/scraper/_types.py
hub_scraper/scraper/habr_scraper.py
hub_scraper-0.6.1.dist-info/entry_points.txt
hub_scraper-0.6.1.dist-info/LICENSE
hub_scraper-0.6.1.dist-info/WHEEL
hub_scraper-0.6.1.dist-info/METADATA
hub_scraper-0.6.1.dist-info/RECORD
